setup.py
wtime/__init__.py
wtime.egg-info/PKG-INFO
wtime.egg-info/SOURCES.txt
wtime.egg-info/dependency_links.txt
wtime.egg-info/entry_points.txt
wtime.egg-info/top_level.txt