Metadata-Version: 2.1
Name: wtime
Version: 0.2
Summary: Week Time
Home-page: http://phyl.io/?page=wtime.html
Author: Philippe Kappel
Author-email: philippe.kappel@gmail.com
License: MIT
Keywords: SVG PNG PDF
Platform: UNKNOWN
Classifier: Development Status :: 3 - Alpha
Classifier: Environment :: Console
Classifier: Intended Audience :: Developers
Classifier: Intended Audience :: End Users/Desktop
Classifier: License :: OSI Approved :: MIT License
Classifier: Natural Language :: English
Classifier: Operating System :: Microsoft :: Windows
Classifier: Operating System :: OS Independent
Classifier: Programming Language :: Python :: 3
Classifier: Programming Language :: Python :: 3.6
Classifier: Programming Language :: Python :: 3.7
Classifier: Programming Language :: Python :: 3.8
Classifier: Topic :: Multimedia :: Graphics
Classifier: Topic :: Office/Business :: Scheduling
Classifier: Topic :: Utilities
